{
  "ingest_source": {
    "id": "8e117893-914d-4663-912c-6b9470a7a2de",
    "source_type": "evernote_html",
    "source_path": "/Users/tang/workbench/article-classifier/backups/2023年6月/投资/维格转债.html",
    "collected_at": "2025-11-09T20:05:18.680257Z",
    "external_id": null,
    "title_hint": null,
    "language_hint": "en",
    "captured_at": null,
    "checksum": "87ce6ce9a6adc5e92af28274d3cb6fafca227e1fba6efb914ea49c672f548abc",
    "status": "pending",
    "notes": {
      "batch_id": null
    }
  },
  "note": {
    "id": "4f33aa0b-d448-4e90-ab8b-37700e748858",
    "ingest_source_id": "8e117893-914d-4663-912c-6b9470a7a2de",
    "canonical_title": "维格转债",
    "language": "en",
    "ingested_at": "2025-11-09T20:05:18.680261Z",
    "created_at": null,
    "status": "active",
    "importance": 0,
    "attributes": {
      "source_filename": "维格转债.html"
    }
  },
  "variants": [
    {
      "id": "35300bde-41c4-49ba-95b6-7393e0bb1b3a",
      "note_id": "4f33aa0b-d448-4e90-ab8b-37700e748858",
      "variant_type": "raw_html",
      "version": 1,
      "created_by": "evernote_ingest:v0",
      "created_at": "2025-11-09T20:05:18.680264Z",
      "content": "---\ntitle: 维格转债\nupdated: 2020-07-27 02:31:58Z\ncreated: 2020-07-27 02:31:37Z\nauthor: tangyongfeng@gmail.com\n---\n\n\n<en-note><div>资不抵债，有违约风险</div></en-note>      ",
      "content_path": null,
      "diff_base_variant_id": null,
      "metadata": {
        "checksum": "87ce6ce9a6adc5e92af28274d3cb6fafca227e1fba6efb914ea49c672f548abc",
        "path": "/Users/tang/workbench/article-classifier/backups/2023年6月/投资/维格转债.html"
      }
    },
    {
      "id": "663a70fd-dcc0-4768-98b0-bba3db01c34f",
      "note_id": "4f33aa0b-d448-4e90-ab8b-37700e748858",
      "variant_type": "clean_text",
      "version": 1,
      "created_by": "evernote_ingest:v0",
      "created_at": "2025-11-09T20:05:18.680268Z",
      "content": "---\ntitle: 维格转债\nupdated: 2020-07-27 02:31:58Z\ncreated: 2020-07-27 02:31:37Z\nauthor: tangyongfeng@gmail.com\n---\n\n资不抵债，有违约风险",
      "content_path": null,
      "diff_base_variant_id": null,
      "metadata": {
        "language": "en",
        "length": 122,
        "rule_count": 0,
        "applied_rules": []
      }
    }
  ],
  "extractions": [],
  "journal": {
    "id": "55c7b14e-0ba1-413f-a9d3-dd6227febd8a",
    "note_id": "4f33aa0b-d448-4e90-ab8b-37700e748858",
    "stage": "ingest",
    "agent_id": "evernote_ingest:v0",
    "started_at": "2025-11-09T20:05:18.680273Z",
    "finished_at": "2025-11-09T20:05:18.680273Z",
    "status": "success",
    "input_ref": {
      "task_id": "481eb289-4d1e-45d6-957d-81dec7c927a5",
      "source_path": "/Users/tang/workbench/article-classifier/backups/2023年6月/投资/维格转债.html",
      "checksum": "87ce6ce9a6adc5e92af28274d3cb6fafca227e1fba6efb914ea49c672f548abc"
    },
    "output_ref": {
      "ingest_source": "8e117893-914d-4663-912c-6b9470a7a2de",
      "note": "4f33aa0b-d448-4e90-ab8b-37700e748858",
      "variants": [
        "35300bde-41c4-49ba-95b6-7393e0bb1b3a",
        "663a70fd-dcc0-4768-98b0-bba3db01c34f"
      ]
    },
    "error_detail": null
  }
}