{
  "ingest_source": {
    "id": "a3cbe88d-aff8-403e-919d-c252c6416f83",
    "source_type": "evernote_html",
    "source_path": "/Users/tang/workbench/article-classifier/backups/2023年6月/中彩相关/双色球中奖面6.7%-8.48-9%%.html",
    "collected_at": "2025-11-09T20:05:17.020499Z",
    "external_id": null,
    "title_hint": null,
    "language_hint": "en",
    "captured_at": null,
    "checksum": "87413e184c44550f25adadf6beccacb8bffb399a5095c0f1dba451c82aaf5f65",
    "status": "pending",
    "notes": {
      "batch_id": null
    }
  },
  "note": {
    "id": "3565da5d-ba55-43ad-9537-730fcabe43cb",
    "ingest_source_id": "a3cbe88d-aff8-403e-919d-c252c6416f83",
    "canonical_title": "双色球中奖面6.7%-8.48-9%%",
    "language": "en",
    "ingested_at": "2025-11-09T20:05:17.020503Z",
    "created_at": null,
    "status": "active",
    "importance": 0,
    "attributes": {
      "source_filename": "双色球中奖面6.7%-8.48-9%%.html"
    }
  },
  "variants": [
    {
      "id": "dc583109-0ff9-45f3-b4f6-cc5fdf88a4a9",
      "note_id": "3565da5d-ba55-43ad-9537-730fcabe43cb",
      "variant_type": "raw_html",
      "version": 1,
      "created_by": "evernote_ingest:v0",
      "created_at": "2025-11-09T20:05:17.020506Z",
      "content": "---\ntitle: 双色球中奖面6.7%-8.48-9%%\nupdated: 2012-09-05 04:31:10Z\ncreated: 2012-09-05 03:34:33Z\ntags:\n  - 3D\n  - 中奖面\n  - 双色球\n---\n\n\n\n\n<en-note STYLE=\"word-wrap: break-word; -webkit-nbsp-mode: space; -webkit-line-break: after-white-space;\">\n双色球中奖面6.7%-8.48-9%%\n<div>3D&nbsp;<span STYLE=\"font-size: 10pt; font-family: 宋体; text-indent: 0mm;\">普通1/1000，组三3/1000，组六6/1000</span></div></en-note>      ",
      "content_path": null,
      "diff_base_variant_id": null,
      "metadata": {
        "checksum": "87413e184c44550f25adadf6beccacb8bffb399a5095c0f1dba451c82aaf5f65",
        "path": "/Users/tang/workbench/article-classifier/backups/2023年6月/中彩相关/双色球中奖面6.7%-8.48-9%%.html"
      }
    },
    {
      "id": "9169ece7-1a6e-46b4-8a2a-91e5812a82ab",
      "note_id": "3565da5d-ba55-43ad-9537-730fcabe43cb",
      "variant_type": "clean_text",
      "version": 1,
      "created_by": "evernote_ingest:v0",
      "created_at": "2025-11-09T20:05:17.020509Z",
      "content": "---\ntitle: 双色球中奖面6.7%-8.48-9%%\nupdated: 2012-09-05 04:31:10Z\ncreated: 2012-09-05 03:34:33Z\ntags:\n  - 3D\n  - 中奖面\n  - 双色球\n---\n\n双色球中奖面6.7%-8.48-9%%\n\n3D \n普通1/1000，组三3/1000，组六6/1000",
      "content_path": null,
      "diff_base_variant_id": null,
      "metadata": {
        "language": "en",
        "length": 176,
        "rule_count": 0,
        "applied_rules": []
      }
    }
  ],
  "extractions": [],
  "journal": {
    "id": "a48e8d05-552e-4d5f-9ace-70aee26bbdb1",
    "note_id": "3565da5d-ba55-43ad-9537-730fcabe43cb",
    "stage": "ingest",
    "agent_id": "evernote_ingest:v0",
    "started_at": "2025-11-09T20:05:17.020514Z",
    "finished_at": "2025-11-09T20:05:17.020514Z",
    "status": "success",
    "input_ref": {
      "task_id": "2fe6a0d0-f97c-4ed6-ac45-f875d7d1ac21",
      "source_path": "/Users/tang/workbench/article-classifier/backups/2023年6月/中彩相关/双色球中奖面6.7%-8.48-9%%.html",
      "checksum": "87413e184c44550f25adadf6beccacb8bffb399a5095c0f1dba451c82aaf5f65"
    },
    "output_ref": {
      "ingest_source": "a3cbe88d-aff8-403e-919d-c252c6416f83",
      "note": "3565da5d-ba55-43ad-9537-730fcabe43cb",
      "variants": [
        "dc583109-0ff9-45f3-b4f6-cc5fdf88a4a9",
        "9169ece7-1a6e-46b4-8a2a-91e5812a82ab"
      ]
    },
    "error_detail": null
  }
}